pytest_codeowners.py
pytest_codeowners-0.1.1.dist-info/LICENSE
pytest_codeowners-0.1.1.dist-info/METADATA
pytest_codeowners-0.1.1.dist-info/WHEEL
pytest_codeowners-0.1.1.dist-info/entry_points.txt
pytest_codeowners-0.1.1.dist-info/top_level.txt
pytest_codeowners-0.1.1.dist-info/RECORD
