Metadata-Version: 2.1
Name: pytest-codeowners
Version: 0.1.1
Summary: Pytest plugin for selecting tests by GitHub CODEOWNERS.
Home-page: https://github.com/Iress/pytest-codeowners
Author: Rodney Marsh
Author-email: rodney.marsh@iress.com
License: Apache Software License 2.0
Platform: UNKNOWN
Classifier: Development Status :: 4 - Beta
Classifier: Framework :: Pytest
Classifier: Intended Audience :: Developers
Classifier: Topic :: Software Development :: Testing
Classifier: Programming Language :: Python
Classifier: Programming Language :: Python :: 3
Classifier: Programming Language :: Python :: 3.8
Classifier: Programming Language :: Python :: 3.9
Classifier: Programming Language :: Python :: 3 :: Only
Classifier: Programming Language :: Python :: Implementation :: CPython
Classifier: Programming Language :: Python :: Implementation :: PyPy
Classifier: License :: OSI Approved :: Apache Software License
Classifier: Operating System :: OS Independent
Requires-Python: >=3.8
Requires-Dist: pytest (>=6.0.0)
Requires-Dist: codeowners
Provides-Extra: dev
Requires-Dist: setuptools (>=38.6) ; extra == 'dev'
Requires-Dist: wheel ; extra == 'dev'
